<?xml version="1.0" encoding="utf-8"?>
<odoo>
    <data noupdate="1">

        <!--Address-->
        <record id="data_combo_box_row_col_types_address" model="report.template.options.combo.box.item">
            <field name="name">Address</field>
            <field name="name_technical">address</field>
            <field name="key">report_utils__row_col_types</field>
        </record>

        <!--Address Secondary Lang-->
        <record id="data_combo_box_row_col_types_address_lang2" model="report.template.options.combo.box.item">
            <field name="name">Address (Secondary Lang)</field>
            <field name="name_technical">address_lang2</field>
            <field name="key">report_utils__row_col_types</field>
        </record>

        <!--Logo-->
        <record id="data_combo_box_row_col_types_logo" model="report.template.options.combo.box.item">
            <field name="name">Logo</field>
            <field name="name_technical">logo</field>
            <field name="key">report_utils__row_col_types</field>
        </record>

        <!--Heading-->
        <record id="data_combo_box_row_col_types_heading" model="report.template.options.combo.box.item">
            <field name="name">Heading</field>
            <field name="name_technical">heading</field>
            <field name="key">report_utils__row_col_types</field>
        </record>

        <!--Tagline-->
        <record id="data_combo_box_row_col_types_tagline" model="report.template.options.combo.box.item">
            <field name="name">Tagline</field>
            <field name="name_technical">tagline</field>
            <field name="key">report_utils__row_col_types</field>
        </record>

        <!--Tagline-->
        <record id="data_combo_box_row_col_types_page_no" model="report.template.options.combo.box.item">
            <field name="name">Page Number</field>
            <field name="name_technical">page_number</field>
            <field name="key">report_utils__row_col_types</field>
        </record>



    </data>
</odoo>